LICENSE
voice_presentation_control/__init__.py
voice_presentation_control/__main__.py
voice_presentation_control/action_matcher.py
voice_presentation_control/cli.py
voice_presentation_control/configs/actions.json
voice_presentation_control/controller.py
voice_presentation_control/mic.py
voice_presentation_control/recognizer.py
voice_presentation_control/vosk_models/en/README
voice_presentation_control/vosk_models/en/am/final.mdl
voice_presentation_control/vosk_models/en/conf/mfcc.conf
voice_presentation_control/vosk_models/en/conf/model.conf
voice_presentation_control/vosk_models/en/graph/Gr.fst
voice_presentation_control/vosk_models/en/graph/HCLr.fst
voice_presentation_control/vosk_models/en/graph/disambig_tid.int
voice_presentation_control/vosk_models/en/graph/phones/word_boundary.int
voice_presentation_control/vosk_models/en/ivector/final.dubm
voice_presentation_control/vosk_models/en/ivector/final.ie
voice_presentation_control/vosk_models/en/ivector/final.mat
voice_presentation_control/vosk_models/en/ivector/global_cmvn.stats
voice_presentation_control/vosk_models/en/ivector/online_cmvn.conf
voice_presentation_control/vosk_models/en/ivector/splice.conf
voice_presentation_control/vosk_models/zh/README
voice_presentation_control/vosk_models/zh/am/final.mdl
voice_presentation_control/vosk_models/zh/conf/mfcc.conf
voice_presentation_control/vosk_models/zh/conf/model.conf
voice_presentation_control/vosk_models/zh/graph/Gr.fst
voice_presentation_control/vosk_models/zh/graph/HCLr.fst
voice_presentation_control/vosk_models/zh/graph/disambig_tid.int
voice_presentation_control/vosk_models/zh/graph/phones/word_boundary.int
voice_presentation_control/vosk_models/zh/ivector/final.dubm
voice_presentation_control/vosk_models/zh/ivector/final.ie
voice_presentation_control/vosk_models/zh/ivector/final.mat
voice_presentation_control/vosk_models/zh/ivector/global_cmvn.stats
voice_presentation_control/vosk_models/zh/ivector/online_cmvn.conf
voice_presentation_control-1.0.2.dist-info/entry_points.txt
voice_presentation_control-1.0.2.dist-info/LICENSE
voice_presentation_control-1.0.2.dist-info/WHEEL
voice_presentation_control-1.0.2.dist-info/METADATA
voice_presentation_control-1.0.2.dist-info/RECORD
