Metadata-Version: 2.1
Name: voice-presentation-control
Version: 1.0.2
Summary: voice-presentation-control is a tool that allows you to control your presentation using voice when you don't have a presentation pen or when it's inconvinient to use the keyboard.
Home-page: https://github.com/wst24365888/voice-presentation-control
License: MIT
Author: Xyphuz
Author-email: xyphuzwu@gmail.com
Requires-Python: >=3.9,<4.0
Classifier: License :: OSI Approved :: MIT License
Classifier: Programming Language :: Python :: 3
Classifier: Programming Language :: Python :: 3.10
Classifier: Programming Language :: Python :: 3.9
Requires-Dist: PyAudio (>=0.2.11,<0.3.0)
Requires-Dist: PyAutoGUI (>=0.9.53,<0.10.0)
Requires-Dist: numpy (>=1.22.3,<2.0.0)
Requires-Dist: typer (>=0.4.1,<0.5.0)
Requires-Dist: vosk (>=0.3.32,<0.4.0)
Project-URL: Repository, https://github.com/wst24365888/voice-presentation-control
